[
    {
        "id": "1",
        "area": "關都",
        "name": "妙蛙種子",
        "type1": "草",
        "type1__class": "grassType",
        "type2": "毒",
        "type2__class": "poisonType",
        "image": "https://godex.site/imgs/pokemon/001.png"
    },
    {
        "id": "152",
        "area": "成都",
        "name": "菊草葉",
        "type1": "草",
        "type1__class": "grassType",
        "type2": "",
        "type2__class": "noneType",
        "image": "https://godex.site/imgs/pokemon/152.png"
    },
    {
        "id": "252",
        "area": "豐緣",
        "name": "木守宮",
        "type1": "草",
        "type1__class": "grassType",
        "type2": "",
        "type2__class": "noneType",
        "image": "https://godex.site/imgs/pokemon/252.png"
    },
    {
        "id": "387",
        "area": "神奧",
        "name": "草苗龜",
        "type1": "草",
        "type1__class": "grassType",
        "type2": "",
        "type2__class": "noneType",
        "image": "https://godex.site/imgs/pokemon/387.png"
    },
    {
        "id": "494",
        "area": "合眾",
        "name": "比克提尼",
        "type1": "超能力",
        "type1__class": "psychicType",
        "type2": "火",
        "type2__class": "fireType",
        "image": "https://godex.site/imgs/pokemon/494.png"
    },
    {
        "id": "650",
        "area": "卡洛斯",
        "name": "哈力栗",
        "type1": "草",
        "type1__class": "grassType",
        "type2": "",
        "type2__class": "noneType",
        "image": "https://godex.site/imgs/pokemon/650-m.png"
    },
    {
        "id": "810",
        "area": "伽勒爾",
        "name": "敲音猴",
        "type1": "草",
        "type1__class": "grassType",
        "type2": "",
        "type2__class": "noneType",
        "image": "https://godex.site/imgs/pokemon/201-qm.png"
    }
]